include/alp/common.hpp
include/alp/config.hpp
include/alp/constants.hpp
include/alp/decoder.hpp
include/alp/encoder.hpp
include/alp/falp.hpp
include/alp/rd.hpp
include/alp/sampler.hpp
include/alp/state.hpp
include/alp.hpp
include/fastlanes.h
include/fastlanes.hpp
include/flatbuffers/allocator.h
include/flatbuffers/array.h
include/flatbuffers/base.h
include/flatbuffers/buffer.h
include/flatbuffers/buffer_ref.h
include/flatbuffers/code_generator.h
include/flatbuffers/code_generators.h
include/flatbuffers/default_allocator.h
include/flatbuffers/detached_buffer.h
include/flatbuffers/file_manager.h
include/flatbuffers/flatbuffer_builder.h
include/flatbuffers/flatbuffers.h
include/flatbuffers/flatc.h
include/flatbuffers/flex_flat_util.h
include/flatbuffers/flexbuffers.h
include/flatbuffers/grpc.h
include/flatbuffers/hash.h
include/flatbuffers/idl.h
include/flatbuffers/minireflect.h
include/flatbuffers/reflection.h
include/flatbuffers/reflection_generated.h
include/flatbuffers/registry.h
include/flatbuffers/stl_emulation.h
include/flatbuffers/string.h
include/flatbuffers/struct.h
include/flatbuffers/table.h
include/flatbuffers/util.h
include/flatbuffers/vector.h
include/flatbuffers/vector_downward.h
include/flatbuffers/verifier.h
include/fls/api/engine.hpp
include/fls/api/exp.hpp
include/fls/api/prm.hpp
include/fls/ccc/thomas.hpp
include/fls/cfg/cfg.hpp
include/fls/common/alias.hpp
include/fls/common/assert.hpp
include/fls/common/bases.hpp
include/fls/common/bimap.hpp
include/fls/common/bimap_frequency.hpp
include/fls/common/byte_c.hpp
include/fls/common/common.hpp
include/fls/common/concept.hpp
include/fls/common/decimal.hpp
include/fls/common/double.hpp
include/fls/common/exception.hpp
include/fls/common/macros.hpp
include/fls/common/magic_enum.hpp
include/fls/common/static_assert.hpp
include/fls/common/status.hpp
include/fls/common/stp.hpp
include/fls/common/string.hpp
include/fls/connection.hpp
include/fls/cor/arch.hpp
include/fls/cor/cpu.hpp
pyfastlanes-0.1.3.post7.dist-info/METADATA
pyfastlanes-0.1.3.post7.dist-info/WHEEL
pyfastlanes-0.1.3.post7.dist-info/licenses/LICENSE
pyfastlanes-0.1.3.post7.dist-info/RECORD
