Metadata-Version: 2.2
Name: pyfastlanes
Version: 0.1.3.post7
Summary: FastLanes File Format
Keywords: fastlanes,file-format
Author-Email: Azim Afroozeh <azim@cwi.nl>
License: MIT License
Requires-Python: >=3.8
